{
	"title": "AutismPhenotype",
	"$schema": "http://json-schema.org/schema#",
	"type": "object",
	"definitions": {
		"ADOS_Module1": {
			"type": "object",
			"properties": {
				"age": {
					"description": "Age in months at interview",
					"type": ["integer", "null"],
					"minimum": 0
				},
				"interview_date": {
					"type": ["string", "null"]
				},
				"diagnosis": {
					"description": "Diagnosis calculated from instrument.",
					"enum": ["Autism", "Autism Spectrum", "Control", null]
				},
				"diagnosis_num_nulls": {
					"description": "Number of null entries encountered when calculating diagnosis.",
					"type": ["integer", "null"],
					"minimum": 0
				},
				"communication": {
					"description": "Communication. Subscore used in assigning diagnosis.",
					"type": ["integer", "null"],
					"minimum": 0,
					"data-type": "score"
				},
				"social_interaction": {
					"description": "Social interaction. Subscore used in assigning diagnosis.",
					"type": ["integer", "null"],
					"minimum": 0,
					"data-type": "score"
				},
				"restricted_repetitive_behavior": {
					"description": "Restricted repetitive behavior. Subscore used in assigning diagnosis.",
					"type": ["integer", "null"],
					"minimum": 0,
					"data-type": "score"
				},
				"QA01": {
					"description": "Overall level of non-echoed spoken language",
					"enum": [null, 0, 1, 2, 3, 4],
					"data-type": "ordinal"
				},
				"QA02": {
					"description": "Frequency of spontaneous vocalization directed to others",
					"enum": [null, 0, 1, 2, 3],
					"data-type": "ordinal"
				},
				"QA03": {
					"description": "Intonation of vocalization or verbalizations",
					"enum": [null, 0, 1, 2],
					"data-type": "ordinal"
				},
				"QA03a": {
					"description": "Coded: Intonation of vocalization or verbalizations",
					"enum": [null, 0, 8],
					"data-type": "categorical"
				},
				"QA04": {
					"description": "Immediate echolalia",
					"enum": [null, 0, 1, 2, 3],
					"data-type": "ordinal"
				},
				"QA04a": {
					"description": "Coded: Immediate echolalia",
					"enum": [null, 0, 8],
					"data-type": "categorical"
				},
				"QA05": {
					"description": "Stereotyped/idiosyncratic use of words or phrases",
					"enum": [null, 0, 1, 2, 3],
					"data-type": "ordinal"
				},
				"QA05a": {
					"description": "Coded: Stereotyped/idiosyncratic use of words or phrases",
					"enum": [null, 0, 8],
					"data-type": "categorical"
				},
				"QA06": {
					"description": "Use of another's body",
					"enum": [null, 0, 1, 2],
					"data-type": "ordinal"
				},
				"QA06a": {
					"description": "Coded: Use of another's body",
					"enum": [null, 0, 8],
					"data-type": "categorical"
				},
				"QA07": {
					"description": "Pointing",
					"enum": [null, 0, 1, 2, 3],
					"data-type": "ordinal"
				},
				"QA08": {
					"description": "Gestures",
					"enum": [null, 0, 1, 2],
					"data-type": "ordinal"
				},
				"QA08a": {
					"description": "Coded: Gestures",
					"enum": [null, 0, 8],
					"data-type": "categorical"
				},
				"QB01": {
					"description": "Unusual eye contact",
					"enum": [null, 0, 2],
					"data-type": "ordinal"
				},
				"QB02": {
					"description": "Responsive social smile",
					"enum": [null, 0, 1, 2, 3],
					"data-type": "ordinal"
				},
				"QB03": {
					"description": "Facial expressions directed to others",
					"enum": [null, 0, 1, 2],
					"data-type": "ordinal"
				},
				"QB04": {
					"description": "Integration of gaze and other behaviors during social overtures",
					"enum": [null, 0, 1, 2, 3],
					"data-type": "ordinal"
				},
				"QB05": {
					"description": "Shared enjoyment in interaction",
					"enum": [null, 0, 1, 2, 3],
					"data-type": "ordinal"
				},
				"QB06": {
					"description": "Response to name",
					"enum": [null, 0, 1, 2, 3],
					"data-type": "ordinal"
				},
				"QB07": {
					"description": "Requesting",
					"enum": [null, 0, 1, 2, 3],
					"data-type": "ordinal"
				},
				"QB08": {
					"description": "Giving",
					"enum": [null, 0, 1, 2],
					"data-type": "ordinal"
				},
				"QB09": {
					"description": "Showing",
					"enum": [null, 0, 1, 2],
					"data-type": "ordinal"
				},
				"QB10": {
					"description": "Spontaneous initiation of joint attention",
					"enum": [null, 0, 1, 2],
					"data-type": "ordinal"
				},
				"QB11": {
					"description": "Response to joint attention",
					"enum": [null, 0, 1, 2, 3],
					"data-type": "ordinal"
				},
				"QB12": {
					"description": "Quality of social overtures",
					"enum": [null, 0, 1, 2, 3],
					"data-type": "ordinal"
				},
				"QB13.1": {
					"description": "Amount of social overtures/maintenance of attention to examiner",
					"enum": [null, 0, 1, 2, 3],
					"data-type": "ordinal"
				},
				"QB13.1a": {
					"description": "Coded: Amount of social overtures/maintenance of attention to examiner",
					"enum": [null, 0, 7],
					"data-type": "categorical"
				},
				"QB13.2": {
					"description": "Amount of social overtures/maintenance of attention to parent",
					"enum": [null, 0, 1, 2, 3],
					"data-type": "ordinal"
				},
				"QB13.2a": {
					"description": "Coded: Amount of social overtures/maintenance of attention to parent",
					"enum": [null, 0, 7, 8],
					"data-type": "categorical"
				},
				"QB14": {
					"description": "Quality of social response",
					"enum": [null, 0, 1, 2, 3],
					"data-type": "ordinal"
				},
				"QB15": {
					"description": "Level of engagement",
					"enum": [null, 0, 1, 2, 3],
					"data-type": "ordinal"
				},
				"QB16": {
					"description": "Overall quality of rapport",
					"enum": [null, 0, 1, 2, 3],
					"data-type": "ordinal"
				},
				"QC01": {
					"description": "Functional play with objects",
					"enum": [null, 0, 1, 2, 3],
					"data-type": "ordinal"
				},
				"QC02": {
					"description": "Imagination/creativity",
					"enum": [null, 0, 1, 2, 3],
					"data-type": "ordinal"
				},
				"QD01": {
					"description": "Unusual sensory interest in play material/person",
					"enum": [null, 0, 1, 2, 3],
					"data-type": "ordinal"
				},
				"QD02": {
					"description": "Hand and finger and other complex mannerisms",
					"enum": [null, 0, 1, 2, 3],
					"data-type": "ordinal"
				},
				"QD03": {
					"description": "Self-injurious behavior",
					"enum": [null, 0, 1, 2],
					"data-type": "ordinal"
				},
				"QD04": {
					"description": "Unusually repetitive interests or stereotyped behaviors",
					"enum": [null, 0, 1, 2, 3],
					"data-type": "ordinal"
				},
				"QE01": {
					"description": "Overactivity",
					"enum": [null, 0, 1, 2, 3],
					"data-type": "ordinal"
				},
				"QE01a": {
					"description": "Coded: Overactivity",
					"enum": [null, 0, 7],
					"data-type": "categorical"
				},
				"QE02": {
					"description": "Tantrums, aggression, negative or disruptive behavior",
					"enum": [null, 0, 1, 2, 3],
					"data-type": "ordinal"
				},
				"QE03": {
					"description": "Anxiety",
					"enum": [null, 0, 1, 2],
					"data-type": "ordinal"
				}
			},
			"additionalProperties": false,
			"required": ["QA01", "QA02", "QA03", "QA03a", "QA04", "QA04a", "QA05", "QA05a", "QA06", "QA06a", "QA07", "QA08", "QA08a", 
			"QB01", "QB02", "QB03", "QB04", "QB05", "QB06", "QB07", "QB08", "QB09", "QB10", "QB11", "QB12", "QB13.1", "QB13.1a", "QB13.2", "QB13.2a", "QB14", "QB15", "QB16", 
			"QC01", "QC02", 
			"QD01", "QD02", "QD03", "QD04", 
			"QE01", "QE01a", "QE02", "QE03",
			"age", "interview_date", "diagnosis", "diagnosis_num_nulls",
			"social_interaction", "communication", "restricted_repetitive_behavior"]
		},
		"ADOS_Module2": {
			"type": "object",
			"properties": {
				"age": {
					"description": "Age in months at interview",
					"type": ["integer", "null"],
					"minimum": 0
				},
				"interview_date": {
					"type": ["string", "null"]
				},
				"diagnosis": {
					"description": "Diagnosis calculated from instrument.",
					"enum": ["Autism", "Autism Spectrum", "Control", null]
				},
				"diagnosis_num_nulls": {
					"description": "Number of null entries encountered when calculating diagnosis.",
					"type": ["integer", "null"],
					"minimum": 0
				},
				"communication": {
					"description": "Communication. Subscore used in assigning diagnosis.",
					"type": ["integer", "null"],
					"minimum": 0,
					"data-type": "score"
				},
				"social_interaction": {
					"description": "Social interaction. Subscore used in assigning diagnosis.",
					"type": ["integer", "null"],
					"minimum": 0,
					"data-type": "score"
				},
				"restricted_repetitive_behavior": {
					"description": "Restricted repetitive behavior. Subscore used in assigning diagnosis.",
					"type": ["integer", "null"],
					"minimum": 0,
					"data-type": "score"
				},
				"QA01": {
					"description": "Overall level of non-echoed spoken language",
					"enum": [null, 0, 1, 2, 3],
					"data-type": "ordinal"
				},
				"QA02": {
					"description": "Speech abnormalities associated with autism (intonation/volume/rhythm/rate",
					"enum": [null, 0, 1, 2],
					"data-type": "ordinal"
				},
				"QA02a": {
					"description": "Coded: Speech abnormalities associated with autism (intonation/volume/rhythm/rate",
					"enum": [null, 0, 7, 8],
					"data-type": "categorical"
				},
				"QA03": {
					"description": "Immediate echolalia",
					"enum": [null, 0, 1, 2, 3],
					"data-type": "ordinal"
				},
				"QA04": {
					"description": "Stereotyped/idiosyncratic use of words or phrases",
					"enum": [null, 0, 1, 2, 3],
					"data-type": "ordinal"
				},
				"QA05": {
					"description": "Conversation",
					"enum": [null, 0, 1, 2, 3],
					"data-type": "ordinal"
				},
				"QA06": {
					"description": "Pointing",
					"enum": [null, 0, 1, 2, 3],
					"data-type": "ordinal"
				},
				"QA07": {
					"description": "Descriptive, conventional, instrumental, or informational gestures",
					"enum": [null, 0, 1, 2, 3],
					"data-type": "ordinal"
				},
				"QA07a": {
					"description": "Coded: Descriptive, conventional, instrumental, or informational gestures",
					"enum": [null, 0, 8],
					"data-type": "categorical"
				},
				"QB01": {
					"description": "Unusual eye contact",
					"enum": [null, 0, 2],
					"data-type": "ordinal"
				},
				"QB02": {
					"description": "Facial expressions directed to others",
					"enum": [null, 0, 1, 2],
					"data-type": "ordinal"
				},
				"QB03": {
					"description": "Shared enjoyment in interaction",
					"enum": [null, 0, 1, 2, 3],
					"data-type": "ordinal"
				},
				"QB04": {
					"description": "Response to name",
					"enum": [null, 0, 1, 2, 3],
					"data-type": "ordinal"
				},
				"QB05": {
					"description": "Showing",
					"enum": [null, 0, 1, 2],
					"data-type": "ordinal"
				},
				"QB06": {
					"description": "Spontaneous initiation of joint attention",
					"enum": [null, 0, 1, 2],
					"data-type": "ordinal"
				},
				"QB07": {
					"description": "Response to joint attention",
					"enum": [null, 0, 1, 2, 3],
					"data-type": "ordinal"
				},
				"QB08": {
					"description": "Quality of social overtures",
					"enum": [null, 0, 1, 2, 3],
					"data-type": "ordinal"
				},
				"QB09.1": {
					"description": "Amount of social overtures/maintenance of attention to examiner",
					"enum": [null, 0, 1, 2, 3],
					"data-type": "ordinal"
				},
				"QB09.1a": {
					"description": "Coded: Amount of social overtures/maintenance of attention to examiner",
					"enum": [null, 0, 7],
					"data-type": "categorical"
				},
				"QB09.2": {
					"description": "Amount of social overtures/maintenance of attention to parent",
					"enum": [null, 0, 1, 2, 3],
					"data-type": "ordinal"
				},
				"QB09.2a": {
					"description": "Coded: Amount of social overtures/maintenance of attention to parent",
					"enum": [null, 0, 7, 8],
					"data-type": "categorical"
				},
				"QB10": {
					"description": "Quality of social response",
					"enum": [null, 0, 1, 2, 3],
					"data-type": "ordinal"
				},
				"QB11": {
					"description": "Amount of reciprocal social communication",
					"enum": [null, 0, 1, 2, 3],
					"data-type": "ordinal"
				},
				"QB12": {
					"description": "Overall quality of rapport",
					"enum": [null, 0, 1, 2, 3],
					"data-type": "ordinal"
				},
				"QC01": {
					"description": "Functional play with objects",
					"enum": [null, 0, 1, 2, 3],
					"data-type": "ordinal"
				},
				"QC02": {
					"description": "Imagination/creativity",
					"enum": [null, 0, 1, 2, 3],
					"data-type": "ordinal"
				},
				"QD01": {
					"description": "Unusual sensory interest in play material/person",
					"enum": [null, 0, 1, 2, 3],
					"data-type": "ordinal"
				},
				"QD02": {
					"description": "Hand and finger and other complex mannerisms",
					"enum": [null, 0, 1, 2, 3],
					"data-type": "ordinal"
				},
				"QD03": {
					"description": "Self-injurious behavior",
					"enum": [null, 0, 1, 2],
					"data-type": "ordinal"
				},
				"QD04": {
					"description": "Unusually repetitive interests or stereotyped behaviors",
					"enum": [null, 0, 1, 2, 3],
					"data-type": "ordinal"
				},
				"QE01": {
					"description": "Overactivity",
					"enum": [null, 0, 1, 2, 3],
					"data-type": "ordinal"
				},
				"QE01a": {
					"description": "Coded: Overactivity",
					"enum": [null, 0, 7],
					"data-type": "categorical"
				},
				"QE02": {
					"description": "Tantrums, aggression, negative or disruptive behavior",
					"enum": [null, 0, 1, 2, 3],
					"data-type": "ordinal"
				},
				"QE03": {
					"description": "Anxiety",
					"enum": [null, 0, 1, 2],
					"data-type": "ordinal"
				}
			},
			"additionalProperties": false,
			"required": ["QA01", "QA02", "QA02a", "QA03", "QA04", "QA05", "QA06", "QA07", "QA07a", 
			"QB01", "QB02", "QB03", "QB04", "QB05", "QB06", "QB07", "QB08", "QB09.1", "QB09.1a", "QB09.2", "QB09.2a", "QB10", "QB11", "QB12", 
			"QC01", "QC02", 
			"QD01", "QD02", "QD03", "QD04", 
			"QE01", "QE01a", "QE02", "QE03",
			"age", "interview_date", "diagnosis", "diagnosis_num_nulls",
			"social_interaction", "communication", "restricted_repetitive_behavior"]

		},
		"ADOS_Module3": {
			"type": "object",
			"properties": {
				"age": {
					"description": "Age in months at interview",
					"type": ["integer", "null"],
					"minimum": 0
				},
				"interview_date": {
					"type": ["string", "null"]
				},
				"diagnosis": {
					"description": "Diagnosis calculated from instrument.",
					"enum": ["Autism", "Autism Spectrum", "Control", null]
				},
				"diagnosis_num_nulls": {
					"description": "Number of null entries encountered when calculating diagnosis.",
					"type": ["integer", "null"],
					"minimum": 0
				},
				"communication": {
					"description": "Communication. Subscore used in assigning diagnosis.",
					"type": ["integer", "null"],
					"minimum": 0,
					"data-type": "score"
				},
				"social_interaction": {
					"description": "Social interaction. Subscore used in assigning diagnosis.",
					"type": ["integer", "null"],
					"minimum": 0,
					"data-type": "score"
				},
				"restricted_repetitive_behavior": {
					"description": "Restricted repetitive behavior. Subscore used in assigning diagnosis.",
					"type": ["integer", "null"],
					"minimum": 0,
					"data-type": "score"
				},
				"QA01": {
					"description": "Overall level of non-echoed spoken language",
					"enum": [null, 0, 1, 2, 3],
					"data-type": "ordinal"
				},
				"QA02": {
					"description": "Speech abnormalities associated with autism (intonation/volume/rhythm/rate",
					"enum": [null, 0, 1, 2],
					"data-type": "ordinal"
				},
				"QA02a": {
					"description": "Coded: Speech abnormalities associated with autism (intonation/volume/rhythm/rate",
					"enum": [null, 0, 7],
					"data-type": "categorical"
				},
				"QA03": {
					"description": "Immediate echolalia",
					"enum": [null, 0, 1, 2, 3],
					"data-type": "ordinal"
				},
				"QA04": {
					"description": "Stereotyped/idiosyncratic use of words or phrases",
					"enum": [null, 0, 1, 2, 3],
					"data-type": "ordinal"
				},
				"QA05": {
					"description": "Offers information",
					"enum": [null, 0, 1, 2],
					"data-type": "ordinal"
				},
				"QA06": {
					"description": "Asks for information",
					"enum": [null, 0, 1, 2, 3],
					"data-type": "ordinal"
				},
				"QA07": {
					"description": "Reporting of events",
					"enum": [null, 0, 1, 2, 3],
					"data-type": "ordinal"
				},
				"QA08": {
					"description": "Conversation",
					"enum": [null, 0, 1, 2, 3],
					"data-type": "ordinal"
				},
				"QA09": {
					"description": "Descriptive, conventional, instrumental, or informational gestures",
					"enum": [null, 0, 1, 2, 3],
					"data-type": "ordinal"
				},
				"QA09a": {
					"description": "Coded: Descriptive, conventional, instrumental, or informational gestures",
					"enum": [null, 0, 8],
					"data-type": "categorical"
				},
				"QB01": {
					"description": "Unusual eye contact",
					"enum": [null, 0, 2],
					"data-type": "ordinal"
				},
				"QB02": {
					"description": "Facial expressions directed to examiner",
					"enum": [null, 0, 1, 2],
					"data-type": "ordinal"
				},
				"QB03": {
					"description": "Language production and linked nonverbal communication",
					"enum": [null, 0, 1, 2],
					"data-type": "ordinal"
				},
				"QB03a": {
					"description": "Coded: Language production and linked nonverbal communication",
					"enum": [null, 0, 7, 8],
					"data-type": "categorical"
				},
				"QB04": {
					"description": "Shared enjoyment in interaction",
					"enum": [null, 0, 1, 2, 3],
					"data-type": "ordinal"
				},
				"QB05": {
					"description": "Comments on others' emotions/empathy",
					"enum": [null, 0, 1, 2],
					"data-type": "ordinal"
				},
				"QB06": {
					"description": "Insight into typical social situations and relationships",
					"enum": [null, 0, 1, 2, 3],
					"data-type": "ordinal"
				},
				"QB07": {
					"description": "Quality of social overtures",
					"enum": [null, 0, 1, 2, 3],
					"data-type": "ordinal"
				},
				"QB08": {
					"description": "Amount of social overtures/maitenance of attention",
					"enum": [null, 0, 1, 2, 3],
					"data-type": "ordinal"
				},
				"QB08a": {
					"description": "Coded: Amount of social overtures/maitenance of attention",
					"enum": [null, 0, 7],
					"data-type": "categorical"
				},
				"QB09": {
					"description": "Quality of social response",
					"enum": [null, 0, 1, 2, 3],
					"data-type": "ordinal"
				},
				"QB10": {
					"description": "Amount of reciprocal social communication",
					"enum": [null, 0, 1, 2, 3],
					"data-type": "ordinal"
				},
				"QB11": {
					"description": "Overall quality of rapport",
					"enum": [null, 0, 1, 2, 3],
					"data-type": "ordinal"
				},
				"QC01": {
					"description": "Imagination/creativity",
					"enum": [null, 0, 1, 2, 3],
					"data-type": "ordinal"
				},
				"QD01": {
					"description": "Unusual sensory interest in play material/person",
					"enum": [null, 0, 1, 2, 3],
					"data-type": "ordinal"
				},
				"QD02": {
					"description": "Hand and finger and other complex mannerisms",
					"enum": [null, 0, 1, 2, 3],
					"data-type": "ordinal"
				},
				"QD03": {
					"description": "Self-injurious behavior",
					"enum": [null, 0, 1, 2],
					"data-type": "ordinal"
				},
				"QD04": {
					"description": "Excessive interest in or references to unusual or highly specific topics or objects or repetitive behaviors",
					"enum": [null, 0, 1, 2, 3],
					"data-type": "ordinal"
				},
				"QD05": {
					"description": "Compulsions or rituals",
					"enum": [null, 0, 1, 2],
					"data-type": "ordinal"
				},
				"QE01": {
					"description": "Overactivity/agitation",
					"enum": [null, 0, 1, 2, 3],
					"data-type": "ordinal"
				},
				"QE01a": {
					"description": "Coded: Overactivity",
					"enum": [null, 0, 7],
					"data-type": "categorical"
				},
				"QE02": {
					"description": "Tantrums, aggression, negative or disruptive behavior",
					"enum": [null, 0, 1, 2, 3],
					"data-type": "ordinal"
				},
				"QE03": {
					"description": "Anxiety",
					"enum": [null, 0, 1, 2],
					"data-type": "ordinal"
				}
			},
			"additionalProperties": false,
			"required": ["QA01", "QA02", "QA02a", "QA03", "QA04", "QA05", "QA06", "QA07", "QA08", "QA09", "QA09a",
			"QB01", "QB02", "QB03", "QB03a", "QB04", "QB05", "QB06", "QB07", "QB08", "QB08a", "QB09", "QB10", "QB11", 
			"QC01", 
			"QD01", "QD02", "QD03", "QD04", "QD05", 
			"QE01", "QE01a", "QE02", "QE03",
			"age", "interview_date", "diagnosis", "diagnosis_num_nulls",
			"social_interaction", "communication", "restricted_repetitive_behavior"]
		},
		"ADOS_Module4": {
			"type": "object",
			"properties": {
				"age": {
					"description": "Age in months at interview",
					"type": ["integer", "null"],
					"minimum": 0
				},
				"interview_date": {
					"type": ["string", "null"]
				},
				"diagnosis": {
					"description": "Diagnosis calculated from instrument.",
					"enum": ["Autism", "Autism Spectrum", "Control", null]
				},
				"diagnosis_num_nulls": {
					"description": "Number of null entries encountered when calculating diagnosis.",
					"type": ["integer", "null"],
					"minimum": 0
				},
				"communication": {
					"description": "Communication. Subscore used in assigning diagnosis.",
					"type": ["integer", "null"],
					"minimum": 0,
					"data-type": "score"
				},
				"social_interaction": {
					"description": "Social interaction. Subscore used in assigning diagnosis.",
					"type": ["integer", "null"],
					"minimum": 0,
					"data-type": "score"
				},
				"restricted_repetitive_behavior": {
					"description": "Restricted repetitive behavior. Subscore used in assigning diagnosis.",
					"type": ["integer", "null"],
					"minimum": 0,
					"data-type": "score"
				},
				"QA01": {
					"description": "Overall level of non-echoed spoken language",
					"enum": [null, 0, 1, 2, 3],
					"data-type": "ordinal"
				},
				"QA02": {
					"description": "Speech abnormalities associated with autism (intonation/volume/rhythm/rate",
					"enum": [null, 0, 1, 2],
					"data-type": "ordinal"
				},
				"QA02a": {
					"description": "Coded: Speech abnormalities associated with autism (intonation/volume/rhythm/rate",
					"enum": [null, 0, 7],
					"data-type": "categorical"
				},
				"QA03": {
					"description": "Immediate echolalia",
					"enum": [null, 0, 1, 2, 3],
					"data-type": "ordinal"
				},
				"QA04": {
					"description": "Stereotyped/idiosyncratic use of words or phrases",
					"enum": [null, 0, 1, 2, 3],
					"data-type": "ordinal"
				},
				"QA05": {
					"description": "Offers information",
					"enum": [null, 0, 1, 2],
					"data-type": "ordinal"
				},
				"QA06": {
					"description": "Asks for information",
					"enum": [null, 0, 1, 2, 3],
					"data-type": "ordinal"
				},
				"QA07": {
					"description": "Reporting of events",
					"enum": [null, 0, 1, 2, 3],
					"data-type": "ordinal"
				},
				"QA08": {
					"description": "Conversation",
					"enum": [null, 0, 1, 2, 3],
					"data-type": "ordinal"
				},
				"QA09": {
					"description": "Descriptive, conventional, instrumental, or informational gestures",
					"enum": [null, 0, 1, 2, 3],
					"data-type": "ordinal"
				},
				"QA09a": {
					"description": "Coded: Descriptive, conventional, instrumental, or informational gestures",
					"enum": [null, 0, 8],
					"data-type": "categorical"
				},
				"QA10": {
					"description": "Emphatic or emotional gestures",
					"enum": [null, 0, 1, 2, 3],
					"data-type": "ordinal"
				},
				"QA10a": {
					"description": "Coded: Emphatic or emotional gestures",
					"enum": [null, 0, 8],
					"data-type": "categorical"
				},
				"QB01": {
					"description": "Unusual eye contact",
					"enum": [null, 0, 2],
					"data-type": "ordinal"
				},
				"QB02": {
					"description": "Facial expressions directed to examiner",
					"enum": [null, 0, 1, 2],
					"data-type": "ordinal"
				},
				"QB03": {
					"description": "Language production and linked nonverbal communication",
					"enum": [null, 0, 1, 2],
					"data-type": "ordinal"
				},
				"QB03a": {
					"description": "Coded: Language production and linked nonverbal communication",
					"enum": [null, 0, 7, 8],
					"data-type": "categorical"
				},
				"QB04": {
					"description": "Shared enjoyment in interaction",
					"enum": [null, 0, 1, 2, 3],
					"data-type": "ordinal"
				},
				"QB05": {
					"description": "Communication of own affect",
					"enum": [null, 0, 1, 2, 3],
					"data-type": "ordinal"
				},
				"QB06": {
					"description": "Comments on others' emotions/empathy",
					"enum": [null, 0, 1, 2],
					"data-type": "ordinal"
				},
				"QB07": {
					"description": "Insight into typical social situations and relationships",
					"enum": [null, 0, 1, 2, 3],
					"data-type": "ordinal"
				},
				"QB08": {
					"description": "Responsibility",
					"enum": [null, 0, 1, 2],
					"data-type": "ordinal"
				},
				"QB09": {
					"description": "Quality of social overtures",
					"enum": [null, 0, 1, 2, 3],
					"data-type": "ordinal"
				},
				"QB10": {
					"description": "Amount of social overtures/maintenance of attention",
					"enum": [null, 0, 1, 2, 3],
					"data-type": "ordinal"
				},
				"QB10a": {
					"description": "Coded: Amount of social overtures/maintenance of attention",
					"enum": [null, 0, 7],
					"data-type": "categorical"
				},
				"QB11": {
					"description": "Quality of social response",
					"enum": [null, 0, 1, 2, 3],
					"data-type": "ordinal"
				},
				"QB12": {
					"description": "Amount of reciprocal social communication",
					"enum": [null, 0, 1, 2, 3],
					"data-type": "ordinal"
				},
				"QB13": {
					"description": "Overall quality of rapport",
					"enum": [null, 0, 1, 2, 3],
					"data-type": "ordinal"
				},
				"QC01": {
					"description": "Imagination/creativity",
					"enum": [null, 0, 1, 2, 3],
					"data-type": "ordinal"
				},
				"QD01": {
					"description": "Unusual sensory interest in play material/person",
					"enum": [null, 0, 1, 2, 3],
					"data-type": "ordinal"
				},
				"QD02": {
					"description": "Hand and finger and other complex mannerisms",
					"enum": [null, 0, 1, 2, 3],
					"data-type": "ordinal"
				},
				"QD03": {
					"description": "Self-injurious behavior",
					"enum": [null, 0, 1, 2],
					"data-type": "ordinal"
				},
				"QD04": {
					"description": "Excessive interest in or references to unusual or highly specific topics or objects or repetitive behaviors",
					"enum": [null, 0, 1, 2, 3],
					"data-type": "ordinal"
				},
				"QD05": {
					"description": "Compulsions or rituals",
					"enum": [null, 0, 1, 2],
					"data-type": "ordinal"
				},
				"QE01": {
					"description": "Overactivity/agitation",
					"enum": [null, 0, 1, 2, 3],
					"data-type": "ordinal"
				},
				"QE01a": {
					"description": "Coded: Overactivity",
					"enum": [null, 0, 7],
					"data-type": "categorical"
				},
				"QE02": {
					"description": "Tantrums, aggression, negative or disruptive behavior",
					"enum": [null, 0, 1, 2, 3],
					"data-type": "ordinal"
				},
				"QE03": {
					"description": "Anxiety",
					"enum": [null, 0, 1, 2],
					"data-type": "ordinal"
				}
			},
			"additionalProperties": false,
			"required": ["QA01", "QA02", "QA02a", "QA03", "QA04", "QA05", "QA06", "QA07", "QA08", "QA09", "QA09a", "QA10", "QA10a",
			"QB01", "QB02", "QB03", "QB03a", "QB04", "QB05", "QB06", "QB07", "QB08", "QB09", "QB10", "QB10a", "QB11", "QB12", "QB13",
			"QC01", 
			"QD01", "QD02", "QD03", "QD04", "QD05", 
			"QE01", "QE01a", "QE02", "QE03",
			"age", "interview_date", "diagnosis", "diagnosis_num_nulls",
			"social_interaction", "communication", "restricted_repetitive_behavior"]
		},
		"ADOS": {
			"type": "object",
			"properties": {
				"age": {
					"description": "Age in months at interview",
					"type": ["integer", "null"],
					"minimum": 0
				},
				"interview_date": {
					"type": ["string", "null"]
				},
				"module": {
					"type": "string"
				},
				"diagnosis": {
					"description": "Diagnosis calculated from instrument.",
					"enum": ["Autism", "Autism Spectrum", "Control", null]
				},
				"diagnosis_num_nulls": {
					"description": "Number of null entries encountered when calculating diagnosis.",
					"type": ["integer", "null"],
					"minimum": 0
				},
				"communication": {
					"description": "Communication. Subscore used in assigning diagnosis.",
					"type": ["integer", "null"],
					"minimum": 0,
					"data-type": "score"
				},
				"social_interaction": {
					"description": "Social interaction. Subscore used in assigning diagnosis.",
					"type": ["integer", "null"],
					"minimum": 0,
					"data-type": "score"
				},
				"restricted_repetitive_behavior": {
					"description": "Restricted repetitive behavior. Subscore used in assigning diagnosis.",
					"type": ["integer", "null"],
					"minimum": 0,
					"data-type": "score"
				},
				"QA01": {
					"description": "Overall level of non-echoed spoken language",
					"enum": [null, 0, 1, 2, 3, 4],
					"data-type": "ordinal"
				},
				"QA02": {
					"description": "Speech abnormalities associated with autism (intonation/volume/rhythm/rate",
					"enum": [null, 0, 1, 2],
					"data-type": "ordinal"
				},
				"QA03": {
					"description": "Immediate echolalia",
					"enum": [null, 0, 1, 2, 3],
					"data-type": "ordinal"
				},
				"QA04": {
					"description": "Stereotyped/idiosyncratic use of words or phrases",
					"enum": [null, 0, 1, 2, 3],
					"data-type": "ordinal"
				},
				"QA05": {
					"description": "Offers information",
					"enum": [null, 0, 1, 2],
					"data-type": "ordinal"
				},
				"QA06": {
					"description": "Asks for information",
					"enum": [null, 0, 1, 2, 3],
					"data-type": "ordinal"
				},
				"QA07": {
					"description": "Pointing",
					"enum": [null, 0, 1, 2, 3],
					"data-type": "ordinal"
				},
				"QA08": {
					"description": "Reporting of events",
					"enum": [null, 0, 1, 2, 3],
					"data-type": "ordinal"
				},
				"QA09": {
					"description": "Conversation",
					"enum": [null, 0, 1, 2, 3],
					"data-type": "ordinal"
				},
				"QA10": {
					"description": "Descriptive, conventional, instrumental, or informational gestures",
					"enum": [null, 0, 1, 2, 3],
					"data-type": "ordinal"
				},
				"QA11": {
					"description": "Frequency of spontaneous vocalization directed to others",
					"enum": [null, 0, 1, 2, 3],
					"data-type": "ordinal"
				},
				"QA12": {
					"description": "Use of another's body",
					"enum": [null, 0, 1, 2],
					"data-type": "ordinal"
				},
				"QA13": {
					"description": "Emphatic or emotional gestures",
					"enum": [null, 0, 1, 2, 3],
					"data-type": "ordinal"
				},
				"QB01": {
					"description": "Unusual eye contact",
					"enum": [null, 0, 2],
					"data-type": "ordinal"
				},
				"QB02": {
					"description": "Facial expressions directed to examiner",
					"enum": [null, 0, 1, 2],
					"data-type": "ordinal"
				},
				"QB03": {
					"description": "Language production and linked nonverbal communication",
					"enum": [null, 0, 1, 2],
					"data-type": "ordinal"
				},
				"QB04": {
					"description": "Shared enjoyment in interaction",
					"enum": [null, 0, 1, 2, 3],
					"data-type": "ordinal"
				},
				"QB05": {
					"description": "Comments on others' emotions/empathy",
					"enum": [null, 0, 1, 2],
					"data-type": "ordinal"
				},
				"QB06": {
					"description": "Insight into typical social situations and relationships",
					"enum": [null, 0, 1, 2, 3],
					"data-type": "ordinal"
				},
				"QB07": {
					"description": "Response to name",
					"enum": [null, 0, 1, 2, 3],
					"data-type": "ordinal"
				},
				"QB08": {
					"description": "Showing",
					"enum": [null, 0, 1, 2],
					"data-type": "ordinal"
				},
				"QB09": {
					"description": "Response to joint attention",
					"enum": [null, 0, 1, 2, 3],
					"data-type": "ordinal"
				},
				"QB10": {
					"description": "Spontaneous initiation of joint attention",
					"enum": [null, 0, 1, 2],
					"data-type": "ordinal"
				},
				"QB11": {
					"description": "Amount of social overtures/maitenance of attention",
					"enum": [null, 0, 1, 2, 3],
					"data-type": "ordinal"
				},
				"QB12": {
					"description": "Amount of reciprocal social communication",
					"enum": [null, 0, 1, 2, 3],
					"data-type": "ordinal"
				},
				"QB13": {
					"description": "Quality of social overtures",
					"enum": [null, 0, 1, 2, 3],
					"data-type": "ordinal"
				},
				"QB14": {
					"description": "Quality of social response",
					"enum": [null, 0, 1, 2, 3],
					"data-type": "ordinal"
				},
				"QB15": {
					"description": "Overall quality of rapport",
					"enum": [null, 0, 1, 2, 3],
					"data-type": "ordinal"
				},
				"QB16": {
					"description": "Integration of gaze and other behaviors during social overtures",
					"enum": [null, 0, 1, 2, 3],
					"data-type": "ordinal"
				},
				"QB17": {
					"description": "Responsive social smile",
					"enum": [null, 0, 1, 2, 3],
					"data-type": "ordinal"
				},
				"QB18": {
					"description": "Communication of own affect",
					"enum": [null, 0, 1, 2, 3],
					"data-type": "ordinal"
				},
				"QB19": {
					"description": "Requesting",
					"enum": [null, 0, 1, 2, 3],
					"data-type": "ordinal"
				},
				"QB20": {
					"description": "Responsibility",
					"enum": [null, 0, 1, 2],
					"data-type": "ordinal"
				},
				"QB21": {
					"description": "Giving",
					"enum": [null, 0, 1, 2],
					"data-type": "ordinal"
				},
				"QB22": {
					"description": "Level of engagement",
					"enum": [null, 0, 1, 2, 3],
					"data-type": "ordinal"
				},
				"QB23": {
					"description": "Amount of social overtures/maintenance of attention to parent",
					"enum": [null, 0, 1, 2, 3],
					"data-type": "ordinal"
				},
				"QC01": {
					"description": "Functional play with objects",
					"enum": [null, 0, 1, 2, 3],
					"data-type": "ordinal"
				},
				"QC02": {
					"description": "Imagination/creativity",
					"enum": [null, 0, 1, 2, 3],
					"data-type": "ordinal"
				},
				"QD01": {
					"description": "Unusual sensory interest in play material/person",
					"enum": [null, 0, 1, 2, 3],
					"data-type": "ordinal"
				},
				"QD02": {
					"description": "Hand and finger and other complex mannerisms",
					"enum": [null, 0, 1, 2, 3],
					"data-type": "ordinal"
				},
				"QD03": {
					"description": "Self-injurious behavior",
					"enum": [null, 0, 1, 2],
					"data-type": "ordinal"
				},
				"QD04": {
					"description": "Excessive interest in or references to unusual or highly specific topics or objects or repetitive behaviors",
					"enum": [null, 0, 1, 2, 3],
					"data-type": "ordinal"
				},
				"QD05": {
					"description": "Compulsions or rituals",
					"enum": [null, 0, 1, 2],
					"data-type": "ordinal"
				},
				"QE01": {
					"description": "Overactivity/agitation",
					"enum": [null, 0, 1, 2, 3],
					"data-type": "ordinal"
				},
				"QE02": {
					"description": "Tantrums, aggression, negative or disruptive behavior",
					"enum": [null, 0, 1, 2],
					"data-type": "ordinal"
				},
				"QE03": {
					"description": "Anxiety",
					"enum": [null, 0, 1, 2],
					"data-type": "ordinal"
				}
			},
			"additionalProperties": false,
			"required": ["QA01", "QA02", "QA03", "QA04", "QA05", "QA06", "QA07", "QA08", "QA09", "QA10", "QA11", "QA12", "QA13",
			"QB01", "QB02", "QB03", "QB04", "QB05", "QB06", "QB07", "QB08", "QB09", "QB10", "QB11", "QB12", "QB13", "QB14", "QB15", "QB16", "QB17", "QB18", "QB19", "QB20", "QB21", "QB22", "QB23",
			"QC01", "QC02", 
			"QD01", "QD02", "QD03", "QD04", "QD05", 
			"QE01", "QE02", "QE03",
			"age", "module", "interview_date", "diagnosis", "diagnosis_num_nulls",
			"social_interaction", "communication", "restricted_repetitive_behavior"]
		},
		"SRS": {
			"type": "object",
			"properties": {
				"respondent": {
					"description": "Interview respondent",
					"enum": ["Parent", "Teacher", "Mother", "Father", "Other relative", "Other specialist", null]
				},
				"age": {
					"description": "Age in months at interview",
					"type": ["integer", "null"],
					"minimum": 0
				},
				"interview_date": {
					"type": ["string", "null"]
				},
				"diagnosis": {
					"description": "Diagnosis calculated from instrument.",
					"enum": ["Autism", "Autism Spectrum", "Control", null]
				},
				"diagnosis_num_nulls": {
					"description": "Number of null entries encountered when calculating diagnosis.",
					"type": ["integer", "null"],
					"minimum": 0
				},
				"social_awareness": {
					"description": "Social awareness. Subscore used in assigning diagnosis.",
					"type": ["integer", "null"],
					"minimum": 0,
					"data-type": "score"
				},
				"social_cognition": {
					"description": "Social cognition. Subscore used in assigning diagnosis.",
					"type": ["integer", "null"],
					"minimum": 0,
					"data-type": "score"
				},
				"social_communication": {
					"description": "Social communication. Subscore used in assigning diagnosis.",
					"type": ["integer", "null"],
					"minimum": 0,
					"data-type": "score"
				},
				"social_motivation": {
					"description": "Social motivation. Subscore used in assigning diagnosis.",
					"type": ["integer", "null"],
					"minimum": 0,
					"data-type": "score"
				},
				"autistic_mannerisms": {
					"description": "Autistic mannerisms. Subscore used in assigning diagnosis.",
					"type": ["integer", "null"],
					"minimum": 0,
					"data-type": "score"
				},
				"total_raw_score": {
					"description": "Raw score. Subscore used in assigning diagnosis.",
					"type": ["integer", "null"],
					"minimum": 0,
					"data-type": "score"
				},
				"total_t_score": {
					"description": "T score. Subscore used in assigning diagnosis.",
					"type": ["integer", "null"],
					"minimum": 0,
					"data-type": "score"
				},
				"Q01": {
					"description": "Seems much more fidgety in social situations than when alone.",
					"enum": [null, 0, 1, 2, 3],
					"data-type": "ordinal"
				},
				"Q02": {
					"description": "Expressions on his or her face don't match what he or she is saying.",
					"enum": [null, 0, 1, 2, 3],
					"data-type": "ordinal"
				},
				"Q03": {
					"description": "Seems self-confident when interacting with others.",
					"enum": [null, 0, 1, 2, 3],
					"data-type": "ordinal"
				},
				"Q04": {
					"description": "When under stress, he or she shows rigid or inflexible patterns of behavior that seem odd.",
					"enum": [null, 0, 1, 2, 3],
					"data-type": "ordinal"
				},
				"Q05": {
					"description": "Doesn't recognize when others are trying to take advantage of him or her.",
					"enum": [null, 0, 1, 2, 3],
					"data-type": "ordinal"
				},
				"Q06": {
					"description": "Would rather be alone than with others.",
					"enum": [null, 0, 1, 2, 3],
					"data-type": "ordinal"
				},
				"Q07": {
					"description": "Is aware of what others are thinking or feeling.",
					"enum": [null, 0, 1, 2, 3],
					"data-type": "ordinal"
				},
				"Q08": {
					"description": "Behaves in ways that seem strange or bizarre.",
					"enum": [null, 0, 1, 2, 3],
					"data-type": "ordinal"
				},
				"Q09": {
					"description": "Clings to adults, seems too dependent on them.",
					"enum": [null, 0, 1, 2, 3],
					"data-type": "ordinal"
				},
				"Q10": {
					"description": "Takes things too literally and doesn't get the real meaning of a conversation.",
					"enum": [null, 0, 1, 2, 3],
					"data-type": "ordinal"
				},
				"Q11": {
					"description": "Has good self-confidence.",
					"enum": [null, 0, 1, 2, 3],
					"data-type": "ordinal"
				},
				"Q12": {
					"description": "Is able to communicate his or her feelins to others.",
					"enum": [null, 0, 1, 2, 3],
					"data-type": "ordinal"
				},
				"Q13": {
					"description": "Is akward in turn-taking interactions with peers.",
					"enum": [null, 0, 1, 2, 3],
					"data-type": "ordinal"
				},
				"Q14": {
					"description": "Is not well coordinated.",
					"enum": [null, 0, 1, 2, 3],
					"data-type": "ordinal"
				},
				"Q15": {
					"description": "Is able to understand the meaning of other people's tone of voice and facial expressions.",
					"enum": [null, 0, 1, 2, 3],
					"data-type": "ordinal"
				},
				"Q16": {
					"description": "Avoids eye contact or has unusual eye contact.",
					"enum": [null, 0, 1, 2, 3],
					"data-type": "ordinal"
				},
				"Q17": {
					"description": "Recognizes when something is unfair.",
					"enum": [null, 0, 1, 2, 3],
					"data-type": "ordinal"
				},
				"Q18": {
					"description": "Has difficulty making friends, even when trying his or her best.",
					"enum": [null, 0, 1, 2, 3],
					"data-type": "ordinal"
				},
				"Q19": {
					"description": "Gets frustrated trying to get ideas across in conversations.",
					"enum": [null, 0, 1, 2, 3],
					"data-type": "ordinal"
				},
				"Q20": {
					"description": "Shows unusual sensory interests or strange ways of playing with toys.",
					"enum": [null, 0, 1, 2, 3],
					"data-type": "ordinal"
				},
				"Q21": {
					"description": "Is able to imitate others' actions.",
					"enum": [null, 0, 1, 2, 3],
					"data-type": "ordinal"
				},
				"Q22": {
					"description": "Plays appropriately with children his or her age.",
					"enum": [null, 0, 1, 2, 3],
					"data-type": "ordinal"
				},
				"Q23": {
					"description": "Does not join group activities unless told to do so.",
					"enum": [null, 0, 1, 2, 3],
					"data-type": "ordinal"
				},
				"Q24": {
					"description": "Has more difficulty than other children with changes in his or her routine.",
					"enum": [null, 0, 1, 2, 3],
					"data-type": "ordinal"
				},
				"Q25": {
					"description": "Doesn't seem to mind being out of step with others.",
					"enum": [null, 0, 1, 2, 3],
					"data-type": "ordinal"
				},
				"Q26": {
					"description": "Offers comfort to others when they are sad.",
					"enum": [null, 0, 1, 2, 3],
					"data-type": "ordinal"
				},
				"Q27": {
					"description": "Avoids starting social interactions with peers or adults.",
					"enum": [null, 0, 1, 2, 3],
					"data-type": "ordinal"
				},
				"Q28": {
					"description": "Thinks or talks about the same thing over and over.",
					"enum": [null, 0, 1, 2, 3],
					"data-type": "ordinal"
				},
				"Q29": {
					"description": "Is regarded by other children as odd or weird.",
					"enum": [null, 0, 1, 2, 3],
					"data-type": "ordinal"
				},
				"Q30": {
					"description": "Becomes upset in a sitaution with lots of things going on.",
					"enum": [null, 0, 1, 2, 3],
					"data-type": "ordinal"
				},
				"Q31": {
					"description": "Can't get his or her mind off somethign once he or she starts thinking about it.",
					"enum": [null, 0, 1, 2, 3],
					"data-type": "ordinal"
				},
				"Q32": {
					"description": "Has good personal hygiene.",
					"enum": [null, 0, 1, 2, 3],
					"data-type": "ordinal"
				},
				"Q33": {
					"description": "Is socially awkward, even when he or she is trying to be polite.",
					"enum": [null, 0, 1, 2, 3],
					"data-type": "ordinal"
				},
				"Q34": {
					"description": "Avoids people who want to be emotionally close to him or her.",
					"enum": [null, 0, 1, 2, 3],
					"data-type": "ordinal"
				},
				"Q35": {
					"description": "Has trouble keeping up with the flow of a normal conversation.",
					"enum": [null, 0, 1, 2, 3],
					"data-type": "ordinal"
				},
				"Q36": {
					"description": "Bas difficulty relating to adults.",
					"enum": [null, 0, 1, 2, 3],
					"data-type": "ordinal"
				},
				"Q37": {
					"description": "Has difficulty relating to peers.",
					"enum": [null, 0, 1, 2, 3],
					"data-type": "ordinal"
				},
				"Q38": {
					"description": "Responds appropriately to mood changes in others.",
					"enum": [null, 0, 1, 2, 3],
					"data-type": "ordinal"
				},
				"Q39": {
					"description": "Has an unusually narrow range of interests.",
					"enum": [null, 0, 1, 2, 3],
					"data-type": "ordinal"
				},
				"Q40": {
					"description": "Is imaginative, good at pretending.",
					"enum": [null, 0, 1, 2, 3],
					"data-type": "ordinal"
				},
				"Q41": {
					"description": "Wanders aimlessly from one activity to another.",
					"enum": [null, 0, 1, 2, 3],
					"data-type": "ordinal"
				},
				"Q42": {
					"description": "Seems overly sensitive to sounds, textures, or smells.",
					"enum": [null, 0, 1, 2, 3],
					"data-type": "ordinal"
				},
				"Q43": {
					"description": "Separates easily from caregivers.",
					"enum": [null, 0, 1, 2, 3],
					"data-type": "ordinal"
				},
				"Q44": {
					"description": "Doesn't understand how events relate to one another.",
					"enum": [null, 0, 1, 2, 3],
					"data-type": "ordinal"
				},
				"Q45": {
					"description": "Focuses his or her attention to where others are looking or listening.",
					"enum": [null, 0, 1, 2, 3],
					"data-type": "ordinal"
				},
				"Q46": {
					"description": "Has overly serious facial expressions.",
					"enum": [null, 0, 1, 2, 3],
					"data-type": "ordinal"
				},
				"Q47": {
					"description": "Is too silly or laughs inappropriately.",
					"enum": [null, 0, 1, 2, 3],
					"data-type": "ordinal"
				},
				"Q48": {
					"description": "Has a sense of humor, understands jokes.",
					"enum": [null, 0, 1, 2, 3],
					"data-type": "ordinal"
				},
				"Q49": {
					"description": "Does extremely well at a few tasks, but does not do as well at most other tasks.",
					"enum": [null, 0, 1, 2, 3],
					"data-type": "ordinal"
				},
				"Q50": {
					"description": "Has repetitive, odd behaviors such as hand flapping or rocking.",
					"enum": [null, 0, 1, 2, 3],
					"data-type": "ordinal"
				},
				"Q51": {
					"description": "Has difficulty answering questions directly and ends up talking around the subject.",
					"enum": [null, 0, 1, 2, 3],
					"data-type": "ordinal"
				},
				"Q52": {
					"description": "Knows when he or she is talking too loud or making too much noise.",
					"enum": [null, 0, 1, 2, 3],
					"data-type": "ordinal"
				},
				"Q53": {
					"description": "Talks to people with an unusual tone of voice.",
					"enum": [null, 0, 1, 2, 3],
					"data-type": "ordinal"
				},
				"Q54": {
					"description": "Seems to react to people as if they are objects.",
					"enum": [null, 0, 1, 2, 3],
					"data-type": "ordinal"
				},
				"Q55": {
					"description": "Knows when he or she is too close to someone or invading someone's space.",
					"enum": [null, 0, 1, 2, 3],
					"data-type": "ordinal"
				},
				"Q56": {
					"description": "Walks in between two people who are talking.",
					"enum": [null, 0, 1, 2, 3],
					"data-type": "ordinal"
				},
				"Q57": {
					"description": "Gets teased a lot.",
					"enum": [null, 0, 1, 2, 3],
					"data-type": "ordinal"
				},
				"Q58": {
					"description": "Concentrates too much on parts of things rather than seeing the whole picture.",
					"enum": [null, 0, 1, 2, 3],
					"data-type": "ordinal"
				},
				"Q59": {
					"description": "Is overly suspicious.",
					"enum": [null, 0, 1, 2, 3],
					"data-type": "ordinal"
				},
				"Q60": {
					"description": "Is emotionally distant, doesn't show his or her feelings.",
					"enum": [null, 0, 1, 2, 3],
					"data-type": "ordinal"
				},
				"Q61": {
					"description": "Is inflexible, has a hard time changing his or her mind.",
					"enum": [null, 0, 1, 2, 3],
					"data-type": "ordinal"
				},
				"Q62": {
					"description": "Gives unusual or illogical reasons for doing things.",
					"enum": [null, 0, 1, 2, 3],
					"data-type": "ordinal"
				},
				"Q63": {
					"description": "Touches others in an unusual way.",
					"enum": [null, 0, 1, 2, 3],
					"data-type": "ordinal"
				},
				"Q64": {
					"description": "Is too tense in social settings,",
					"enum": [null, 0, 1, 2, 3],
					"data-type": "ordinal"
				},
				"Q65": {
					"description": "Stares or gazes off into space.",
					"enum": [null, 0, 1, 2, 3],
					"data-type": "ordinal"
				}
			},
			"additionalProperties": false,
			"required": ["Q01", "Q02", "Q03", "Q04", "Q05", "Q06", "Q07", "Q08", "Q09", "Q10", 
						"Q11", "Q12", "Q13", "Q14", "Q15", "Q16", "Q17", "Q18", "Q19", "Q20",
						"Q21", "Q22", "Q23", "Q24", "Q25", "Q26", "Q27", "Q28", "Q29", "Q30",
						"Q31", "Q32", "Q33", "Q34", "Q35", "Q36", "Q37", "Q38", "Q39", "Q40",
						"Q41", "Q42", "Q43", "Q44", "Q45", "Q46", "Q47", "Q48", "Q49", "Q50",
						"Q51", "Q52", "Q53", "Q54", "Q55", "Q56", "Q57", "Q58", "Q59", "Q60",
						"Q61", "Q62", "Q63", "Q64", "Q65",
						"age", "interview_date", "diagnosis", "diagnosis_num_nulls", "total_raw_score", "total_t_score",
						"social_awareness", "social_cognition", "social_communication", "social_motivation", "autistic_mannerisms"]
		},
		"SCQ": {
			"type": "object",
			"properties": {
				"interview_date": {
					"type": ["string", "null"]
				},
				"Q01": {
					"description": "Talk",
					"enum": [null, 0, 1],
					"data-type": "ordinal"
				},
				"Q02": {
					"description": "To from conversation",
					"enum": [null, 0, 1],
					"data-type": "ordinal"
				},
				"Q03": {
					"description": "Odd phrases",
					"enum": [null, 0, 1],
					"data-type": "ordinal"
				},
				"Q04": {
					"description": "Socially inappropriate",
					"enum": [null, 0, 1],
					"data-type": "ordinal"
				},
				"Q05": {
					"description": "Mixed pronouns",
					"enum": [null, 0, 1],
					"data-type": "ordinal"
				},
				"Q06": {
					"description": "Invents words",
					"enum": [null, 0, 1],
					"data-type": "ordinal"
				},
				"Q07": {
					"description": "Repeats",
					"enum": [null, 0, 1],
					"data-type": "ordinal"
				},
				"Q08": {
					"description": "Particular way",
					"enum": [null, 0, 1],
					"data-type": "ordinal"
				},
				"Q09": {
					"description": "Appropriate facial",
					"enum": [null, 0, 1],
					"data-type": "ordinal"
				},
				"Q10": {
					"description": "Hand tools",
					"enum": [null, 0, 1],
					"data-type": "ordinal"
				},
				"Q11": {
					"description": "Odd interests",
					"enum": [null, 0, 1],
					"data-type": "ordinal"
				},
				"Q12": {
					"description": "Interest parts",
					"enum": [null, 0, 1],
					"data-type": "ordinal"
				},
				"Q13": {
					"description": "Special interests",
					"enum": [null, 0, 1],
					"data-type": "ordinal"
				},
				"Q14": {
					"description": "Sensory interests",
					"enum": [null, 0, 1],
					"data-type": "ordinal"
				},
				"Q15": {
					"description": "Odd manor",
					"enum": [null, 0, 1],
					"data-type": "ordinal"
				},
				"Q16": {
					"description": "Complicated move",
					"enum": [null, 0, 1],
					"data-type": "ordinal"
				},
				"Q17": {
					"description": "Injure self",
					"enum": [null, 0, 1],
					"data-type": "ordinal"
				},
				"Q18": {
					"description": "Carry objects",
					"enum": [null, 0, 1],
					"data-type": "ordinal"
				},
				"Q19": {
					"description": "Friends",
					"enum": [null, 0, 1],
					"data-type": "ordinal"
				},
				"Q20": {
					"description": "Friendly talk",
					"enum": [null, 0, 1],
					"data-type": "ordinal"
				},
				"Q21": {
					"description": "Spontaneous copy",
					"enum": [null, 0, 1],
					"data-type": "ordinal"
				},
				"Q22": {
					"description": "Spontaneous point",
					"enum": [null, 0, 1],
					"data-type": "ordinal"
				},
				"Q23": {
					"description": "Gesture",
					"enum": [null, 0, 1],
					"data-type": "ordinal"
				},
				"Q24": {
					"description": "Node head",
					"enum": [null, 0, 1],
					"data-type": "ordinal"
				},
				"Q25": {
					"description": "Shake head",
					"enum": [null, 0, 1],
					"data-type": "ordinal"
				},
				"Q26": {
					"description": "Look face",
					"enum": [null, 0, 1],
					"data-type": "ordinal"
				},
				"Q27": {
					"description": "Smile",
					"enum": [null, 0, 1],
					"data-type": "ordinal"
				},
				"Q28": {
					"description": "Engage attention",
					"enum": [null, 0, 1],
					"data-type": "ordinal"
				},
				"Q29": {
					"description": "Share",
					"enum": [null, 0, 1],
					"data-type": "ordinal"
				},
				"Q30": {
					"description": "Join",
					"enum": [null, 0, 1],
					"data-type": "ordinal"
				},
				"Q31": {
					"description": "Comfort",
					"enum": [null, 0, 1],
					"data-type": "ordinal"
				},
				"Q32": {
					"description": "Gesture with sound",
					"enum": [null, 0, 1],
					"data-type": "ordinal"
				},
				"Q33": {
					"description": "Facial range",
					"enum": [null, 0, 1],
					"data-type": "ordinal"
				},
				"Q34": {
					"description": "Copy in social game",
					"enum": [null, 0, 1],
					"data-type": "ordinal"
				},
				"Q35": {
					"description": "Play pretend",
					"enum": [null, 0, 1],
					"data-type": "ordinal"
				},
				"Q36": {
					"description": "Interest in other children",
					"enum": [null, 0, 1],
					"data-type": "ordinal"
				},
				"Q37": {
					"description": "Positive approach",
					"enum": [null, 0, 1],
					"data-type": "ordinal"
				},
				"Q38": {
					"description": "Look up talking",
					"enum": [null, 0, 1],
					"data-type": "ordinal"
				},
				"Q39": {
					"description": "Imaginary games",
					"enum": [null, 0, 1],
					"data-type": "ordinal"
				},
				"Q40": {
					"description": "Cooperative play",
					"enum": [null, 0, 1],
					"data-type": "ordinal"
				}
			}
		},
		"Medical History": {
			"type": "object",
			"properties": {
				"ID": {
					"description": "Secondary diagnosis of ID (ex. fragile X, speech delay, aphasia)",
					"enum": [null, 0, 1],
					"data-type": "binary"
				},
				"Seizures": {
					"description": "Secondary diagnosis of seizures (ex. epilepsy, absence seizures, Landau-Kleffner syndrome)",
					"enum": [null, 0, 1],
					"data-type": "binary"
				},
				"Tourette or Tic Disorder": {
					"description": "Secondary diagnosis of Tourette or tic disorder",
					"enum": [null, 0, 1],
					"data-type": "binary"
				},
				"Mood Disorder": {
					"description": "Secondary diagnosis of mood disorder (ex. depression, bipolar)",
					"enum": [null, 0, 1],
					"data-type": "binary"
				},
				"Anxiety Disorder": {
					"description": "Secondary diagnosis of anxiety disorder (ex. OCD, anxiety, pica)",
					"enum": [null, 0, 1],
					"data-type": "binary"
				},
				"Psychotic Disorder": {
					"description": "Secondary diagnosis of psychotic disorder",
					"enum": [null, 0, 1],
					"data-type": "binary"
				},
				"Autoimmune/Allergic": {
					"description": "Secondary diagnosis of autoimmune/allergic (ex. asthma, allergies, lactose intolerant)",
					"enum": [null, 0, 1],
					"data-type": "binary"
				},
				"Behavior": {
					"description": "Secondary diagnosis of behavior (ex. ADD, ADHD, ODD)",
					"enum": [null, 0, 1],
					"data-type": "binary"
				}
			},
			"additionalProperties": false,
			"required": ["ID", "Seizures", "Tourette or Tic Disorder", "Mood Disorder", "Anxiety Disorder", "Psychotic Disorder", "Autoimmune/Allergic", "Behavior"]
		}
	},
	"properties": {
		"dataset": {
			"type": "string"
		},
		"identifier": {
			"type": "string"
		},
		"gender": {
			"enum": [ "Male", "Female", null ]
		},
		"race": {
			"type": ["string", "null"]
		},
		"ethnicity": {
			"type": ["string", "null"]
		},
		"family": {
			"type": ["string", "null"]
		},
		"ADI_Short": {"$ref": "ADI.json#ADI_Short"},
		"ADI_Long": {"$ref": "ADI.json#ADI_Long"},
		"ADIR": {"$ref": "ADI.json#ADIR"},
		"ADOS": {"$ref": "#/definitions/ADOS"},
		"ADOS_Module1": {"$ref": "#/definitions/ADOS_Module1"},
		"ADOS_Module2": {"$ref": "#/definitions/ADOS_Module2"},
		"ADOS_Module3": {"$ref": "#/definitions/ADOS_Module3"},
		"ADOS_Module4": {"$ref": "#/definitions/ADOS_Module4"},
		"SRS_Adult": {"$ref": "#/definitions/SRS"},
		"SRS_Preschool": {"$ref": "#/definitions/SRS"},
		"SRS_Child": {"$ref": "#/definitions/SRS"},
		"Medical History": {"$ref": "#/definitions/Medical History"},
		"diagnosis": {
			"description": "Overall diagnosis calculated from combination of instruments.",
			"enum": ["Autism", "Control", null]
		},
		"clinical_diagnosis": {
			"description": "Diagnosis given by clinician. Coded value.",
			"enum": ["Autism", "Control", null]
		},
		"clinical_diagnosis_raw": {
			"description": "Original diagnosis given by clinician. Free text.",
			"type": ["string", "null"]
		},
		"cpea_diagnosis": {
			"description": "CPEA diagnosis - combines ADIR and ADOS.",
			"enum": ["Autism", "Autism Spectrum", "Aspergers", "Control", null]
		},
		"cpea_adjusted_diagnosis": {
			"description": "CPEA diagnosis - combines ADIR and ADOS. This diagnosis is adjusted to mark true controls (where both ADOS and ADIR agree that this is a control) from Suspected Control (where ADOS and ADIR disagree).",
			"enum": ["Autism", "Autism Spectrum", "Aspergers", "Control", "Suspected Control", null]
		}
	},
	"required": ["identifier"]
}